cht_tide/__init__.py
cht_tide/astro.py
cht_tide/constituent.py
cht_tide/database.py
cht_tide/fes2014.py
cht_tide/model.py
cht_tide/nodal_corrections.py
cht_tide/read_bca.py
cht_tide/tide.py
cht_tide/tide_predict.py
cht_tide/tide_stations.py
cht_tide-0.1.1.dist-info/LICENSE
cht_tide-0.1.1.dist-info/METADATA
cht_tide-0.1.1.dist-info/WHEEL
cht_tide-0.1.1.dist-info/top_level.txt
cht_tide-0.1.1.dist-info/zip-safe
cht_tide-0.1.1.dist-info/RECORD
