Metadata-Version: 2.2
Name: cht_tide
Version: 0.1.1
Summary: Combining of tidal components to time series
Author-email: Maarten van Ormondt <maarten.vanormondt@deltares.nl>, Julian Hofer <Julian.Hofer@deltares.nl>, Sarwan Peiter <Sarwan.Peiter@deltares.nl>
License: MIT
Project-URL: Source, https://github.com/Deltares/cht_tide
Classifier: Intended Audience :: Science/Research
Classifier: Topic :: Scientific/Engineering :: Hydrology
Requires-Python: >=3.10
License-File: LICENSE
Requires-Dist: numpy
Requires-Dist: scipy
Requires-Dist: toml
Requires-Dist: pandas
Requires-Dist: geopandas
Requires-Dist: boto3
Requires-Dist: cht_utils
Provides-Extra: tests
Requires-Dist: pytest; extra == "tests"
Requires-Dist: matplotlib; extra == "tests"
